imhdsk/__init__.py
imhdsk-0.0.5.dist-info/DESCRIPTION.rst
imhdsk-0.0.5.dist-info/METADATA
imhdsk-0.0.5.dist-info/RECORD
imhdsk-0.0.5.dist-info/WHEEL
imhdsk-0.0.5.dist-info/metadata.json
imhdsk-0.0.5.dist-info/top_level.txt
