Metadata-Version: 2.0
Name: imhdsk
Version: 0.0.5
Summary: An unofficial API for imhd.sk
Home-page: https://github.com/mrshu/python-imhdsk-api
Author: mr.Shu
Author-email: mr@shu.io
License: UNKNOWN
Platform: UNKNOWN
Requires-Dist: lxml
Requires-Dist: requests
